pymef-1.4.6.dist-info/RECORD
pymef-1.4.6.dist-info/WHEEL
pymef-1.4.6.dist-info/top_level.txt
pymef-1.4.6.dist-info/METADATA
pymef-1.4.6.dist-info/licenses/LICENSE.txt
pymef/mef_session.py
pymef/version.py
pymef/__init__.py
pymef/mef_constants.py
pymef/mef_file/pymef3_file.c
pymef/mef_file/__init__.py
pymef/mef_file/pymef3_file.cpython-310-darwin.so
pymef/mef_file/pymef3_file.h
