Metadata-Version: 2.4
Name: pymef
Version: 1.4.6
Summary: Pymef is a wrapper library for Multiscale Electrophysiology Format developed by MSEL laboratory.
Author-email:  Jan Cimbalnik <jan.cimbalnik@fnusa.cz>
License: Apache-2.0
Project-URL: homepage, https://github.com/msel-source/pymef
Project-URL: documentation, https://pymef.readthedocs.io/
Project-URL: repository, https://github.com/msel-source/pymef
Keywords: MEF,Mayo,Electrophysiology
Classifier: Intended Audience :: Science/Research
Classifier: License :: OSI Approved :: Apache Software License
Classifier: Operating System :: OS Independent
Classifier: Programming Language :: Python :: 3
Classifier: Programming Language :: Python :: 3 :: Only
Classifier: Programming Language :: Python :: 3.12
Classifier: Programming Language :: Python :: 3.11
Classifier: Programming Language :: Python :: 3.10
Classifier: Programming Language :: Python :: 3.9
Classifier: Programming Language :: Python :: 3.8
Classifier: Programming Language :: Python :: 3.7
Classifier: Programming Language :: Python :: 3.6
Classifier: Topic :: Scientific/Engineering
Requires-Python: >=3.6
License-File: LICENSE.txt
Requires-Dist: numpy
Dynamic: license-file
